kasa/__init__.py
kasa/cachedzoneinfo.py
kasa/credentials.py
kasa/device.py
kasa/device_factory.py
kasa/device_type.py
kasa/deviceconfig.py
kasa/discover.py
kasa/emeterstatus.py
kasa/exceptions.py
kasa/feature.py
kasa/httpclient.py
kasa/json.py
kasa/module.py
kasa/modulemapping.py
kasa/modulemapping.pyi
kasa/py.typed
kasa/cli/__init__.py
kasa/cli/__main__.py
kasa/cli/common.py
kasa/cli/device.py
kasa/cli/discover.py
kasa/cli/feature.py
kasa/cli/hub.py
kasa/cli/lazygroup.py
kasa/cli/light.py
kasa/cli/main.py
kasa/cli/schedule.py
kasa/cli/time.py
kasa/cli/usage.py
kasa/cli/vacuum.py
kasa/cli/wifi.py
kasa/interfaces/__init__.py
kasa/interfaces/alarm.py
kasa/interfaces/childsetup.py
kasa/interfaces/energy.py
kasa/interfaces/fan.py
kasa/interfaces/led.py
kasa/interfaces/light.py
kasa/interfaces/lighteffect.py
kasa/interfaces/lightpreset.py
kasa/interfaces/thermostat.py
kasa/interfaces/time.py
kasa/iot/__init__.py
kasa/iot/effects.py
kasa/iot/iotbulb.py
kasa/iot/iotcamera.py
kasa/iot/iotdevice.py
kasa/iot/iotdimmer.py
kasa/iot/iotlightstrip.py
kasa/iot/iotmodule.py
kasa/iot/iotplug.py
kasa/iot/iotstrip.py
kasa/iot/iottimezone.py
kasa/iot/modules/__init__.py
kasa/iot/modules/ambientlight.py
kasa/iot/modules/antitheft.py
kasa/iot/modules/cloud.py
kasa/iot/modules/countdown.py
kasa/iot/modules/dimmer.py
kasa/iot/modules/emeter.py
kasa/iot/modules/led.py
kasa/iot/modules/light.py
kasa/iot/modules/lighteffect.py
kasa/iot/modules/lightpreset.py
kasa/iot/modules/motion.py
kasa/iot/modules/rulemodule.py
kasa/iot/modules/schedule.py
kasa/iot/modules/time.py
kasa/iot/modules/usage.py
kasa/protocols/__init__.py
kasa/protocols/iotprotocol.py
kasa/protocols/protocol.py
kasa/protocols/smartcamprotocol.py
kasa/protocols/smartprotocol.py
kasa/smart/__init__.py
kasa/smart/effects.py
kasa/smart/smartchilddevice.py
kasa/smart/smartdevice.py
kasa/smart/smartmodule.py
kasa/smart/modules/__init__.py
kasa/smart/modules/alarm.py
kasa/smart/modules/autooff.py
kasa/smart/modules/batterysensor.py
python_kasa-0.10.1.dist-info/METADATA
python_kasa-0.10.1.dist-info/WHEEL
python_kasa-0.10.1.dist-info/entry_points.txt
python_kasa-0.10.1.dist-info/licenses/LICENSE
python_kasa-0.10.1.dist-info/RECORD
