Metadata-Version: 2.4
Name: python-kasa
Version: 0.10.1
Summary: Python API for TP-Link Kasa and Tapo devices
Project-URL: Homepage, https://github.com/python-kasa/python-kasa
Project-URL: Bug Tracker, https://github.com/python-kasa/python-kasa/issues
Project-URL: Documentation, https://python-kasa.readthedocs.io
Project-URL: Repository, https://github.com/python-kasa/python-kasa
Author: python-kasa developers
License: GPL-3.0-or-later
License-File: LICENSE
Classifier: License :: OSI Approved :: GNU General Public License v3 or later (GPLv3+)
Classifier: Operating System :: OS Independent
Classifier: Programming Language :: Python :: 3
Classifier: Programming Language :: Python :: 3.11
Classifier: Programming Language :: Python :: 3.12
Classifier: Programming Language :: Python :: 3.13
Requires-Python: <4.0,>=3.11
Requires-Dist: aiohttp>=3
Requires-Dist: asyncclick>=8.1.7
Requires-Dist: cryptography>=1.9
Requires-Dist: mashumaro>=3.14
Requires-Dist: tzdata>=2024.2; platform_system == 'Windows'
Provides-Extra: docs
Requires-Dist: docutils>=0.17; extra == 'docs'
Requires-Dist: myst-parser; extra == 'docs'
Requires-Dist: sphinx-rtd-theme~=2.0; extra == 'docs'
Requires-Dist: sphinx>=7.4.7; extra == 'docs'
Requires-Dist: sphinxcontrib-programoutput~=0.0; extra == 'docs'
Provides-Extra: shell
Requires-Dist: ptpython; extra == 'shell'
Requires-Dist: rich; extra == 'shell'
Provides-Extra: speedups
Requires-Dist: kasa-crypt>=0.2.0; extra == 'speedups'
Requires-Dist: orjson>=3.9.1; extra == 'speedups'
